{"cpu_stats": {"cpu_usage": {"total_usage": 0, "usage_in_kernelmode": 0, "usage_in_usermode": 0}, "throttling_data": {"periods": 0, "throttled_periods": 0, "throttled_time": 0}}, "precpu_stats": {"cpu_usage": {"total_usage": 1302534247836, "percpu_usage": [261876694522, 257988914468, 255471306520, 277181141830, 249720095900, 9305007, 3900222, 278065674, 1176558, 991131, 560000, 784500, 759972, 551532, 0, 0], "usage_in_kernelmode": 364890000000, "usage_in_usermode": 904210000000}, "system_cpu_usage": 9864666450000000, "online_cpus": 16, "throttling_data": {"periods": 0, "throttled_periods": 0, "throttled_time": 0}}, "memory_stats": {}}